[
  {
    "club_name": "Al-Gharraf SC",
    "club_logo": "",
    "city_country": "Dhi Qar, Iraq",
    "wiki_url": "https://en.wikipedia.org/wiki/Al-Gharraf_SC"
  },
  {
    "club_name": "Al-Kahrabaa FC",
    "club_logo": "",
    "city_country": "Baghdad, Iraq",
    "wiki_url": "https://en.wikipedia.org/wiki/Al-Kahrabaa_FC"
  },
  {
    "club_name": "Al-Karkh SC",
    "club_logo": "",
    "city_country": "Baghdad, Iraq",
    "wiki_url": "https://en.wikipedia.org/wiki/Al-Karkh_SC"
  },
  {
    "club_name": "Al-Karma",
    "club_logo": "",
    "city_country": "Anbar, Iraq",
    "wiki_url": ""
  },
  {
    "club_name": "Al-Minaa SC",
    "club_logo": "",
    "city_country": "Basra, Iraq",
    "wiki_url": "https://en.wikipedia.org/wiki/Al-Minaa_SC"
  },
  {
    "club_name": "Al-Mosul SC",
    "club_logo": "",
    "city_country": "Mosul, Iraq",
    "wiki_url": "https://en.wikipedia.org/wiki/Al-Mosul_SC"
  },
  {
    "club_name": "Al-Naft SC",
    "club_logo": "",
    "city_country": "Baghdad, Iraq",
    "wiki_url": "https://en.wikipedia.org/wiki/Al-Naft_SC"
  },
  {
    "club_name": "Al-Najaf FC",
    "club_logo": "",
    "city_country": "Najaf, Iraq",
    "wiki_url": "https://en.wikipedia.org/wiki/Al-Najaf_FC"
  },
  {
    "club_name": "Al-Qasim SC",
    "club_logo": "",
    "city_country": "Babil, Iraq",
    "wiki_url": "https://en.wikipedia.org/wiki/Al-Qasim_SC"
  },
  {
    "club_name": "Al-Quwa Al-Jawiya",
    "club_logo": "",
    "city_country": "Baghdad, Iraq",
    "wiki_url": "https://en.wikipedia.org/wiki/Al-Quwa_Al-Jawiya"
  },
  {
    "club_name": "Al-Shorta SC",
    "club_logo": "",
    "city_country": "Baghdad, Iraq",
    "wiki_url": "https://en.wikipedia.org/wiki/Al-Shorta_SC"
  },
  {
    "club_name": "Al-Talaba SC",
    "club_logo": "",
    "city_country": "Baghdad, Iraq",
    "wiki_url": "https://en.wikipedia.org/wiki/Al-Talaba_SC"
  },
  {
    "club_name": "Al-Zawraa SC",
    "club_logo": "",
    "city_country": "Baghdad, Iraq",
    "wiki_url": "https://en.wikipedia.org/wiki/Al-Zawraa_SC"
  },
  {
    "club_name": "Amanat Baghdad",
    "club_logo": "",
    "city_country": "Baghdad, Iraq",
    "wiki_url": "https://en.wikipedia.org/wiki/Amanat_Baghdad_SC"
  },
  {
    "club_name": "Diyala FC",
    "club_logo": "",
    "city_country": "Diyala, Iraq",
    "wiki_url": "https://en.wikipedia.org/wiki/Diyala_SC"
  },
  {
    "club_name": "Duhok SC",
    "club_logo": "",
    "city_country": "Duhok, Iraq",
    "wiki_url": "https://en.wikipedia.org/wiki/Duhok_SC"
  },
  {
    "club_name": "Erbil SC",
    "club_logo": "",
    "city_country": "Erbil, Iraq",
    "wiki_url": "https://en.wikipedia.org/wiki/Erbil_SC"
  },
  {
    "club_name": "Naft Maysan",
    "club_logo": "",
    "city_country": "Maysan, Iraq",
    "wiki_url": "https://en.wikipedia.org/wiki/Naft_Maysan_SC"
  },
  {
    "club_name": "Newroz SC",
    "club_logo": "",
    "city_country": "Sulaymaniyah, Iraq",
    "wiki_url": "https://en.wikipedia.org/wiki/Newroz_SC"
  },
  {
    "club_name": "Zakho SC",
    "club_logo": "",
    "city_country": "Duhok, Iraq",
    "wiki_url": "https://en.wikipedia.org/wiki/Zakho_SC"
  }
]  
